qtsit/__init__.py
qtsit/__main__.py
qtsit/base.py
qtsit/cli.py
qtsit/algorithms/__init__.py
qtsit/algorithms/randomwalk.py
qtsit-0.0.1.dev20240410142519.dist-info/LICENSE
qtsit-0.0.1.dev20240410142519.dist-info/METADATA
qtsit-0.0.1.dev20240410142519.dist-info/WHEEL
qtsit-0.0.1.dev20240410142519.dist-info/top_level.txt
qtsit-0.0.1.dev20240410142519.dist-info/RECORD
